pyksolve/__init__.py
pyksolve/deferred.py
pyksolve/solver.cpython-313-darwin.so
pyksolve-0.0.14.dist-info/RECORD
pyksolve-0.0.14.dist-info/WHEEL
pyksolve-0.0.14.dist-info/top_level.txt
pyksolve-0.0.14.dist-info/METADATA
pyksolve-0.0.14.dist-info/licenses/LICENSE
