Metadata-Version: 2.4
Name: pyksolve
Version: 0.0.14
Summary: Cython wrapper for Klondike-Solver.
Home-page: https://github.com/tcdude/py-klondike-solver
Author: Tiziano Bettio
Author-email: tc@tizilogic.com
Classifier: Programming Language :: Python :: 3
Classifier: License :: OSI Approved :: MIT License
Classifier: Operating System :: OS Independent
Requires-Python: >=3.6
License-File: LICENSE
Dynamic: author
Dynamic: author-email
Dynamic: classifier
Dynamic: description
Dynamic: description-content-type
Dynamic: home-page
Dynamic: license-file
Dynamic: requires-python
Dynamic: summary
